{
  "books": [
    {
      "name": "Pride and Prejudice",
      "author": "Jane Austen",
      "year_published": 1813,
      "category": "Romance",
      "inventory": 1,
      "image_url": "https://upload.wikimedia.org/wikipedia/commons/thumb/1/17/PrideAndPrejudiceTitlePage.jpg/800px-PrideAndPrejudiceTitlePage.jpg"
    },
    {
      "name": "The Bourne Identity",
      "author": "Robert Ludlum",
      "year_published": 1980,
      "category": "Action",
      "inventory": 2,
      "image_url": "https://upload.wikimedia.org/wikipedia/en/6/65/Ludlum_-_The_Bourne_Identity_Coverart.png"
    },
    {
      "name": "The Hunger Games",
      "author": "Suzanne Collins",
      "year_published": 2008,
      "category": "Action",
      "inventory": 2,
      "image_url": "https://upload.wikimedia.org/wikipedia/en/thumb/d/dc/The_Hunger_Games.jpg/220px-The_Hunger_Games.jpg"
    },
    {
      "name": "Gone Girl",
      "author": "Gillian Flynn",
      "year_published": 2012,
      "category": "Mystery",
      "inventory": 3,
      "image_url": "https://upload.wikimedia.org/wikipedia/en/thumb/7/7e/Gone_Girl_%28Flynn_novel%29.jpg/220px-Gone_Girl_%28Flynn_novel%29.jpg"
    },
    {
      "name": "The Da Vinci Code",
      "author": "Dan Brown",
      "year_published": 2003,
      "category": "Mystery",
      "inventory": 3,
      "image_url": "https://upload.wikimedia.org/wikipedia/en/thumb/6/6b/DaVinciCode.jpg/220px-DaVinciCode.jpg"
    },
    {
      "name": "Dune",
      "author": "Frank Herbert",
      "year_published": 1965,
      "category": "Sci-Fi",
      "inventory": 1,
      "image_url": "https://upload.wikimedia.org/wikipedia/en/thumb/d/de/Dune-Frank_Herbert_%281965%29_First_edition.jpg/220px-Dune-Frank_Herbert_%281965%29_First_edition.jpg"
    },
    {
      "name": "The Hobbit",
      "author": "J.R.R. Tolkien",
      "year_published": 1937,
      "category": "Fantasy",
      "inventory": 2,
      "image_url": "https://upload.wikimedia.org/wikipedia/en/thumb/4/4a/TheHobbit_FirstEdition.jpg/220px-TheHobbit_FirstEdition.jpg"
    },
    {
      "name": "The Power of Habit",
      "author": "Charles Duhigg",
      "year_published": 2012,
      "category": "Non-Fiction",
      "inventory": 3,
      "image_url": "https://upload.wikimedia.org/wikipedia/en/thumb/7/7f/The_Power_of_Habit.jpg/220px-The_Power_of_Habit."
    },
    {
      "name": "Educated: A Memoir",
      "author": "Tara Westover",
      "year_published": 2018,
      "category": "Non-Fiction",
      "inventory": 3,
      "image_url": ""
    }
  ],
  "user": [
    {
      "username": "Tal",
      "email": "Tal@example.com",
      "password": "inalog123"
    },
    {
      "username": "Gal",
      "email": "Gal@example.com",
      "password": "inalog123"
    },
    {
      "username": "Ben",
      "email": "Ben@example.com",
      "password": "inalog123"
    }
  ],
  "cart": []
}